mailui/__init__.py
mailui/mailui.py
mailui-0.1.0.dist-info/METADATA
mailui-0.1.0.dist-info/WHEEL
mailui-0.1.0.dist-info/licenses/LICENSE
mailui-0.1.0.dist-info/RECORD
