Metadata-Version: 2.3
Name: mailui
Version: 0.1.0
Summary: Create UIs with emails easily!
Project-URL: Homepage, https://github.com/Milk-Cool/MailUI
Project-URL: Issues, https://github.com/Milk-Cool/MailUI/issues
Author-email: Milk_Cool <coder.tomsk@gmail.com>
Classifier: License :: OSI Approved :: MIT License
Classifier: Operating System :: OS Independent
Classifier: Programming Language :: Python :: 3
Requires-Python: >=3.8
